azure/mgmt/education/__init__.py
azure/mgmt/education/_configuration.py
azure/mgmt/education/_education_management_client.py
azure/mgmt/education/_patch.py
azure/mgmt/education/_serialization.py
azure/mgmt/education/_vendor.py
azure/mgmt/education/_version.py
azure/mgmt/education/py.typed
azure/mgmt/education/aio/__init__.py
azure/mgmt/education/aio/_configuration.py
azure/mgmt/education/aio/_education_management_client.py
azure/mgmt/education/aio/_patch.py
azure/mgmt/education/aio/_vendor.py
azure/mgmt/education/aio/operations/__init__.py
azure/mgmt/education/aio/operations/_education_management_client_operations.py
azure/mgmt/education/aio/operations/_grants_operations.py
azure/mgmt/education/aio/operations/_join_requests_operations.py
azure/mgmt/education/aio/operations/_labs_operations.py
azure/mgmt/education/aio/operations/_operations.py
azure/mgmt/education/aio/operations/_patch.py
azure/mgmt/education/aio/operations/_student_labs_operations.py
azure/mgmt/education/aio/operations/_students_operations.py
azure/mgmt/education/models/__init__.py
azure/mgmt/education/models/_education_management_client_enums.py
azure/mgmt/education/models/_models_py3.py
azure/mgmt/education/models/_patch.py
azure/mgmt/education/operations/__init__.py
azure/mgmt/education/operations/_education_management_client_operations.py
azure/mgmt/education/operations/_grants_operations.py
azure/mgmt/education/operations/_join_requests_operations.py
azure/mgmt/education/operations/_labs_operations.py
azure/mgmt/education/operations/_operations.py
azure/mgmt/education/operations/_patch.py
azure/mgmt/education/operations/_student_labs_operations.py
azure/mgmt/education/operations/_students_operations.py
azure_mgmt_education-1.0.0b2.dist-info/LICENSE
azure_mgmt_education-1.0.0b2.dist-info/METADATA
azure_mgmt_education-1.0.0b2.dist-info/WHEEL
azure_mgmt_education-1.0.0b2.dist-info/top_level.txt
azure_mgmt_education-1.0.0b2.dist-info/RECORD
